{
  "id": 62,
  "name": "Уровень 62",
  "rows": 6,
  "cols": 6,
  "water": [
    [5, 4],
    [2, 5],
    [5, 1],
    [1, 2]
  ],
  "cats": [
    {"type": "Бальзак", "r": 3, "c": 4},
    {"type": "Дон Кихот", "r": 1, "c": 5},
    {"type": "Драйзер", "r": 0, "c": 3},
    {"type": "Жуков", "r": 3, "c": 0},
    {"type": "Драйзер", "r": 5, "c": 2},
    {"type": "Жуков", "r": 4, "c": 4},
    {"type": "Гамлет", "r": 4, "c": 0},
    {"type": "Достоевский", "r": 0, "c": 4},
    {"type": "Гамлет", "r": 1, "c": 4},
    {"type": "Достоевский", "r": 2, "c": 2},
    {"type": "Робеспьер", "r": 3, "c": 5},
    {"type": "Бальзак", "r": 5, "c": 3},
    {"type": "Наполеон", "r": 1, "c": 0},
    {"type": "Бальзак", "r": 2, "c": 0},
    {"type": "Штирлиц", "r": 3, "c": 1},
    {"type": "Наполеон", "r": 0, "c": 0},
    {"type": "Жуков", "r": 5, "c": 5},
    {"type": "Есенин", "r": 2, "c": 1},
    {"type": "Гамлет", "r": 5, "c": 0},
    {"type": "Дюма", "r": 1, "c": 3},
    {"type": "Гамлет", "r": 3, "c": 2}
  ]
}